README.txt
setup.cfg
setup.py
docs/HISTORY.txt
docs/INSTALL.txt
docs/LICENSE.GPL
docs/LICENSE.txt
redomino/__init__.py
redomino.workgroup.egg-info/PKG-INFO
redomino.workgroup.egg-info/SOURCES.txt
redomino.workgroup.egg-info/dependency_links.txt
redomino.workgroup.egg-info/entry_points.txt
redomino.workgroup.egg-info/namespace_packages.txt
redomino.workgroup.egg-info/not-zip-safe
redomino.workgroup.egg-info/paster_plugins.txt
redomino.workgroup.egg-info/requires.txt
redomino.workgroup.egg-info/top_level.txt
redomino/workgroup/HISTORY.txt
redomino/workgroup/README.txt
redomino/workgroup/TODO.txt
redomino/workgroup/__init__.py
redomino/workgroup/config.py
redomino/workgroup/configure.zcml
redomino/workgroup/interfaces.py
redomino/workgroup/permissions.py
redomino/workgroup/permissions.zcml
redomino/workgroup/profiles.zcml
redomino/workgroup/refresh.txt
redomino/workgroup/setuphandlers.py
redomino/workgroup/skins.zcml
redomino/workgroup/tests.py
redomino/workgroup/version.txt
redomino/workgroup/Extensions/Install.py
redomino/workgroup/Extensions/__init__.py
redomino/workgroup/browser/__init__.py
redomino/workgroup/browser/common.py
redomino/workgroup/browser/configure.zcml
redomino/workgroup/browser/memberarea.py
redomino/workgroup/browser/overrides.zcml
redomino/workgroup/browser/search.py
redomino/workgroup/browser/workgroup_form.py
redomino/workgroup/browser/icons/workgroup_icon.gif
redomino/workgroup/browser/templates/member_listing.pt
redomino/workgroup/browser/templates/member_macros.pt
redomino/workgroup/browser/templates/memberarea_view.pt
redomino/workgroup/content/__init__.py
redomino/workgroup/content/configure.zcml
redomino/workgroup/content/memberarea.py
redomino/workgroup/profiles/default/actionicons.xml
redomino/workgroup/profiles/default/actions.xml
redomino/workgroup/profiles/default/browserlayer.xml
redomino/workgroup/profiles/default/componentregistry.xml
redomino/workgroup/profiles/default/factorytool.xml
redomino/workgroup/profiles/default/import_steps.xml
redomino/workgroup/profiles/default/permissions.xml
redomino/workgroup/profiles/default/redomino.workgroup_various.txt
redomino/workgroup/profiles/default/rolemap.xml
redomino/workgroup/profiles/default/skins.xml
redomino/workgroup/profiles/default/types.xml
redomino/workgroup/profiles/default/types/MemberArea.xml
redomino/workgroup/skins/workgroup/createWgMember.cpy
