Metadata-Version: 1.0
Name: redomino.workgroup
Version: 0.1r2
Summary: This product provides a special workgroup mode for the normal Plone Folder to permit the creation of local users.
Home-page: http://www.redomino.com/it/labs/progetti/redomino-workgroup
Author: Davide Moro (Redomino)
Author-email: davide.moro@redomino.com
License: GPL
Platform: UNKNOWN
Classifier: Framework :: Plone
Classifier: Framework :: Zope2
Classifier: Framework :: Zope3
Classifier: Programming Language :: Python
Classifier: Topic :: Software Development :: Libraries :: Python Modules
